yamlx/__init__.py
yamlx/parser.py
yamlx-0.0.8.dist-info/METADATA
yamlx-0.0.8.dist-info/WHEEL
yamlx-0.0.8.dist-info/licenses/LICENSE
yamlx-0.0.8.dist-info/RECORD
