Metadata-Version: 2.4
Name: yamlx
Version: 0.0.8
Summary: Allow variable and expression in YAML file
Author-email: hiroh <hirohata0116@gmail.com>
License-File: LICENSE
Requires-Python: >=3.8
Requires-Dist: omegaconf
Requires-Dist: pyparsing>=3.1.4
Requires-Dist: pyyaml
